quip_spreadsheet/__init__.py
quip_spreadsheet/quip.py
tests/__init__.py
tests/constants.py
tests/test_quip_client.py
quip_spreadsheet-0.5.0b3.dist-info/LICENSE
quip_spreadsheet-0.5.0b3.dist-info/METADATA
quip_spreadsheet-0.5.0b3.dist-info/WHEEL
quip_spreadsheet-0.5.0b3.dist-info/top_level.txt
quip_spreadsheet-0.5.0b3.dist-info/RECORD
