Metadata-Version: 2.1
Name: quip-spreadsheet
Version: 0.5.0b3
Summary: An opinionated client to search, retrieve, and parse Quip spreadsheets.
Home-page: https://github.com/dreamorosi/quip-spreadsheet
Author: Andrea Amorosi
License: UNKNOWN
Platform: UNKNOWN
Classifier: Development Status :: 4 - Beta
Classifier: Intended Audience :: Developers
Classifier: License :: OSI Approved :: MIT License
Classifier: Programming Language :: Python :: 3 :: Only
Classifier: Programming Language :: Python :: 3.7
Classifier: Programming Language :: Python :: 3.8
Classifier: Topic :: Utilities
Classifier: Typing :: Typed
Requires-Python: >=3.7
Requires-Dist: requests (~=2.25)
